rafter_openapi/__init__.py
rafter_openapi/doc.py
rafter_openapi/openapi.py
rafter_openapi/swagger.py
rafter_openapi/ui/favicon-16x16.png
rafter_openapi/ui/favicon-32x32.png
rafter_openapi/ui/index.html
rafter_openapi/ui/oauth2-redirect.html
rafter_openapi/ui/swagger-ui-bundle.js
rafter_openapi/ui/swagger-ui-bundle.js.map
rafter_openapi/ui/swagger-ui-standalone-preset.js
rafter_openapi/ui/swagger-ui-standalone-preset.js.map
rafter_openapi/ui/swagger-ui.css
rafter_openapi/ui/swagger-ui.css.map
rafter_openapi/ui/swagger-ui.js
rafter_openapi/ui/swagger-ui.js.map
rafter_openapi-0.2.0.dist-info/METADATA
rafter_openapi-0.2.0.dist-info/RECORD
rafter_openapi-0.2.0.dist-info/WHEEL
rafter_openapi-0.2.0.dist-info/top_level.txt
